kappaschedules/__init__.py
kappaschedules/factory.py
kappaschedules/schedules/__init__.py
kappaschedules/schedules/constant_schedule.py
kappaschedules/schedules/cosine_decreasing_schedule.py
kappaschedules/schedules/cosine_increasing_schedule.py
kappaschedules/schedules/custom_schedule.py
kappaschedules/schedules/inverse_sqrt_decreasing_schedule.py
kappaschedules/schedules/inverse_sqrt_increasing_schedule.py
kappaschedules/schedules/linear_decreasing_schedule.py
kappaschedules/schedules/linear_increasing_schedule.py
kappaschedules/schedules/linear_warmup_cosine_decay_schedule.py
kappaschedules/schedules/periodic_bool_schedule.py
kappaschedules/schedules/polynomial_decreasing_schedule.py
kappaschedules/schedules/polynomial_increasing_schedule.py
kappaschedules/schedules/sequential_percent_schedule.py
kappaschedules/schedules/sequential_step_schedule.py
kappaschedules/schedules/step_decreasing_schedule.py
kappaschedules/schedules/step_fixed_schedule.py
kappaschedules/schedules/step_interval_schedule.py
kappaschedules/schedules/base/__init__.py
kappaschedules/schedules/base/decreasing_progress_schedule.py
kappaschedules/schedules/base/increasing_progress_schedule.py
kappaschedules/schedules/base/progress_schedule.py
kappaschedules/schedules/base/schedule_base.py
kappaschedules/schedules/functional/__init__.py
kappaschedules/schedules/functional/schedules.py
kappaschedules-0.0.31.dist-info/LICENSE
kappaschedules-0.0.31.dist-info/METADATA
kappaschedules-0.0.31.dist-info/WHEEL
kappaschedules-0.0.31.dist-info/top_level.txt
kappaschedules-0.0.31.dist-info/RECORD
