Metadata-Version: 2.1
Name: kappaschedules
Version: 0.0.31
Summary: schedules
Home-page: https://github.com/BenediktAlkin/KappaSchedules
Project-URL: Source Code, https://github.com/BenediktAlkin/KappaSchedules
Project-URL: Bug Tracker, https://github.com/BenediktAlkin/KappaSchedules/issues
Classifier: Programming Language :: Python :: 3
Classifier: License :: OSI Approved :: MIT License
Classifier: Operating System :: OS Independent
Requires-Python: >=3.6
License-File: LICENSE
